dash/__init__.py
dash/context_processors.py
dash/forms.py
dash/log.py
dash/middleware.py
dash/templates/bootstrap5/field.html
dash/templates/bootstrap5/inputs.html
dash/templates/bootstrap5/layout/checkboxselectmultiple_inline.html
dash/templates/bootstrap5/layout/multifield.html
dash/templates/bootstrap5/layout/radioselect_inline.html
dash/templates/bootstrap5/multifield.html
dash/templates/dash/shared/flash_messages.html
dash/templates/dash/shared/form_errors.html
dash/templates/dash/shared/navbar.html
dash/templates/dash/shared/paginator.html
dash/templatetags/__init__.py
dash/templatetags/dash.py
dash/templatetags/paginator_tags.py
dash/utils/dates.py
dash/utils/files.py
dash/utils/urls.py
abc_dash-0.2.0.dist-info/METADATA
abc_dash-0.2.0.dist-info/WHEEL
abc_dash-0.2.0.dist-info/RECORD
