Metadata-Version: 2.4
Name: abc-dash
Version: 0.2.0
Summary: This package is intended for internal use.
License-Expression: MIT
Author: abc inc.
Requires-Python: >=3.13,<4
Classifier: Programming Language :: Python :: 3
Classifier: Programming Language :: Python :: 3.13
Classifier: Programming Language :: Python :: 3.14
Requires-Dist: django-crispy-forms (>=2.4,<3.0)
Requires-Dist: pathvalidate (>=3.3.1,<4.0.0)
